pydatagovph
