Metadata-Version: 1.1
Name: pydatagovph
Version: 1.4
Summary: Python API Client for data.gov.ph
Home-page: http://ferdinandsilva.com
Author: Ferdinand Silva
Author-email: ferdinandsilva@ferdinandsilva.com
License: UNKNOWN
Download-URL: https://github.com/six519/PyDataGovPH
Platform: UNKNOWN
Classifier: Development Status :: 4 - Beta
Classifier: Intended Audience :: Developers
Classifier: Natural Language :: English
Classifier: Programming Language :: Python
Classifier: License :: Freeware
